the_social_network/__init__.py
the_social_network/admin.py
the_social_network/apps.py
the_social_network/migrations/0001_initial.py
the_social_network/migrations/0002_auto_20211111_1220.py
the_social_network/migrations/__init__.py
the_social_network/models.py
the_social_network/serializers/accountSerializers.py
the_social_network/serializers/authenticationSerializers.py
the_social_network/serializers/contentSerializers.py
the_social_network/tests.py
the_social_network/urls/accountUrls.py
the_social_network/urls/authenticationUrls.py
the_social_network/urls/contentUrls.py
the_social_network/urls/searchUrls.py
the_social_network/validation.py
the_social_network/views/accountViews.py
the_social_network/views/authenticationViews.py
the_social_network/views/contentViews.py
the_social_network/views/searchViews.py
the_social_network-0.0.7.dist-info/LICENSE
the_social_network-0.0.7.dist-info/WHEEL
the_social_network-0.0.7.dist-info/METADATA
the_social_network-0.0.7.dist-info/RECORD
